{
  "id": "estudio-306-estudio-306",
  "slug": "estudio-306-estudio-306",
  "numero_estudio": 306,
  "tipo_estudio": "Iglesia en las casas",
  "ministerio": {
    "iglesia": "Iglesia Cristiana Mega Zoe",
    "pastora": "Pastora Edith Cruz",
    "credito_corto": "Iglesia Cristiana Mega Zoe · Pastora Edith Cruz",
    "credito_largo": "Contenido original de Iglesia Cristiana Mega Zoe, conservando el crédito ministerial correspondiente a la Pastora Edith Cruz."
  },
  "identidad_editorial": {
    "idioma": "es",
    "fuente_original": "documento_word",
    "archivo_origen": "/Users/edwingadiel/Desktop/Estudios en Word/Estudio #306 La tentación de Pedro y su levantarse - Lucas 22 31.doc",
    "estado_revision": "procesado",
    "version_schema": "1.0"
  },
  "encabezado": {
    "titulo": "La Tentación de Pedro y su levantarse",
    "subtitulo": null,
    "cita_principal": "Lucas 22:31",
    "resumen_corto": "La Tentación de Pedro y su levantarse enseña a perseverar en la oración y huir de la tentación."
  },
  "fechas": {
    "fecha_inicio": "2003-07-08",
    "fecha_fin": "2003-07-14",
    "fecha_texto_original": "SEMANA DEL 8 @ 14 DE JULIO DE 2003",
    "ano": 2003
  },
  "clasificacion_biblica": {
    "libro_principal": "Lucas",
    "capitulo_principal": 22,
    "versiculos_principales": [
      31
    ],
    "referencia_principal_normalizada": "Lucas 22:31",
    "testamento_principal": "Nuevo Testamento"
  },
  "clasificacion_tematica": {
    "topicos": [
      "Satanás",
      "Oración",
      "Tentación",
      "Liderazgo espiritual",
      "Familia"
    ],
    "keywords": [
      "vida eterna",
      "oración",
      "juicio",
      "arrepentimiento",
      "escrituras"
    ]
  },
  "referencias_biblicas": [
    {
      "referencia": "Lucas 22:31",
      "referencia_normalizada": "Lucas 22:31",
      "libro": "Lucas",
      "capitulo": 22,
      "versiculos": [
        31
      ],
      "tipo": "principal",
      "clickeable": true
    },
    {
      "referencia": "1 Pedro 5: 8",
      "referencia_normalizada": "1 Pedro 5:8",
      "libro": "1 Pedro",
      "capitulo": 5,
      "versiculos": [
        8
      ],
      "tipo": "secundaria",
      "clickeable": true
    },
    {
      "referencia": "2 Timoteo 3: 16,17",
      "referencia_normalizada": "2 Timoteo 3:16,17",
      "libro": "2 Timoteo",
      "capitulo": 3,
      "versiculos": [
        16,
        17
      ],
      "tipo": "secundaria",
      "clickeable": true
    },
    {
      "referencia": "Lucas 22:24",
      "referencia_normalizada": "Lucas 22:24",
      "libro": "Lucas",
      "capitulo": 22,
      "versiculos": [
        24
      ],
      "tipo": "secundaria",
      "clickeable": true
    },
    {
      "referencia": "2 Corintios 13: 5",
      "referencia_normalizada": "2 Corintios 13:5",
      "libro": "2 Corintios",
      "capitulo": 13,
      "versiculos": [
        5
      ],
      "tipo": "secundaria",
      "clickeable": true
    },
    {
      "referencia": "Gálatas 3: 13, 14",
      "referencia_normalizada": "Gálatas 3:13,14",
      "libro": "Gálatas",
      "capitulo": 3,
      "versiculos": [
        13,
        14
      ],
      "tipo": "secundaria",
      "clickeable": true
    },
    {
      "referencia": "Juan 10: 10",
      "referencia_normalizada": "Juan 10:10",
      "libro": "Juan",
      "capitulo": 10,
      "versiculos": [
        10
      ],
      "tipo": "secundaria",
      "clickeable": true
    },
    {
      "referencia": "Efesios 6: 11,12",
      "referencia_normalizada": "Efesios 6:11,12",
      "libro": "Efesios",
      "capitulo": 6,
      "versiculos": [
        11,
        12
      ],
      "tipo": "secundaria",
      "clickeable": true
    },
    {
      "referencia": "Hebreos 11:6",
      "referencia_normalizada": "Hebreos 11:6",
      "libro": "Hebreos",
      "capitulo": 11,
      "versiculos": [
        6
      ],
      "tipo": "secundaria",
      "clickeable": true
    }
  ],
  "contenido": {
    "introduccion": null,
    "secciones": [],
    "contenido_completo": "Detrás de cada guerra, sea cuál sea, Satanás está. Tenemos que saberlo y entenderlo, que nuestra lucha es con Satanás, por eso tenemos que vivir conscientes de lo que dice la Escritura. Pues el diablo está detrás de cada divorcio, de cada vicio, de cada mala decisión que tomamos, etc. Él siempre está buscando cómo destruir nuestras vidas, día y noche, para después que te destruya burlarse de ti. (1 Pedro 5: 8) Pero la Iglesia tiene tres poderosas armas para romper con los planes de nuestro enemigo el diablo: el ayuno, la oración y conocer las Escrituras. Si conociéramos las Escrituras sabríamos qué hacer cuando el mal nos asecha. (2 Timoteo 3: 16,17) Pero lamentablemente, casi siempre hacemos otra cosa, buscamos a otro para que nos escuche y nos aconseje. Mientras los apóstoles discutían sobre lo que era superficial, quien sería el mayor entre ellos (Lucas 22:24), Satanás buscaba como podía destruirlos uno a uno. Y posiblemente dijo: \"Atacaré al más vulnerable, al más fácil, ¡Atacaré a Pedro!\" (Lucas 22:31) Satanás pidió eso y se le concedió. Cuando nos convertimos de nuestros malos caminos, Satanás comienza a hacer planes para ver cómo nos hace retroceder y cómo nos puede destruir. Entonces, busca lo más frágil, lo más vulnerable en nosotros. Es por eso que tenemos que estar conscientes de quiénes somos y cómo somos. En medio de los apóstoles ya Satanás había destruido a uno (a Judas), ya lo había tumbado, pues lo conquistó por sus ambiciones, por su avaricia. Satanás había observado bien a Judas, descubrió su mal, sus tendencias al mal, las cuales usaría para destruirlo. Por eso debemos examinarnos y renunciar a lo que nos puede hacer caer. (2 Corintios 13: 5) Ten en cuenta que lo que Satanás sugiere a nuestros oídos, a la mente, tú lo puedes resistir. Cuando cedes es porque te place, pues ninguna tentación es sobrenatural, todas son humanas, pues con la tentación tenemos siempre la salida para que podamos soportar (1ra Cor. 10:13). Día y noche él está acusando a los hijos de Dios delante del trono sobre el carácter, sobre nuestras malas obras, sobre la murmuración, etc. No le demos lugar al diablo. Iglesia, no existe ninguna razón para ceder ante la tentación. ¿Es tan grande la pasión para pecar? ¿Por qué ceder si luego vamos a llorar y a lamentar? Si luego será la vergüenza. ¿Serán más grandes la vil tentación y el deseo hacia lo malo que el amor de Jesús? ¿Entregaré yo mi vida al mal así porque sí? Consideremos que el Padre quitó la desgracia de nuestras vidas. Me ha cuidado, me ha dado vida eterna, quitó la maldición (Gálatas 3: 13, 14) y todos los juicios. Entonces, ¿cómo yo voy a ceder a la tentación si el Padre me ha dado tanto? Pesemos en balanza cuál es más grande, ¿la tentación que el diablo nos tiende para destruirnos o el amor que el Padre ha tenido con nuestras vidas? El Padre prepara todo lo que es puro, todo lo bueno. Él es justo, fiel. Por el otro lado, Satanás prepara con traición, con burla, con todo lo que es sucio, prepara para todo lo que te va a causar vergüenza, dolor, daño para ti y para los que están a tu alrededor. Dentro de nosotros hay una batalla de la carne y el espíritu y es más fácil ceder a todo lo que es carne. Cuando cedemos vamos rumbo a la destrucción, y después al pasar el tiempo decimos, \"Fue que no pude.\" No debe ser. Pues hay algo que se llama \"tiempo\", y el \"tiempo\" trae la vejez y junto con la vejez se van las fuerzas, el ánimo, el deseo de hacer lo bueno, la capacidad de poder actuar bien que se va con los días, y Satanás vino y destruyó lo que era el plan de Dios, el plan perfecto. No te engañes tú mismo. Sucede que decimos que lo que es correcto es lo que nosotros pensamos y creemos. Pero eso es producto de nuestro orgullo. Y a veces nos convertimos en el apoyo de lo que está mal. No apoyes nunca lo malo, porque cuando lo hacemos estamos diciéndole al mal, \"Ven entra a mi casa.\" Aunque te digan que eres muy estricto, que eres muy fuerte, no permitas entrar el mal a tu casa, porque Satanás viene para matar, robar y destruir. (Juan 10: 10) Pedro no entendió lo que Jesús le advertía, \"Pedro, Satanás te ha pedido para zarandearos, pero yo he rogado por ti, que tu fe no falte.\" Y pensar que nosotros tomamos la vida como si fuera tan fácil y la luchamos a flor de piel y pasamos la vida como un juego y los días como si nada, y nos olvidamos de Dios, de los dones que nos da, de los ministerios. Y muchos se ocupan más en jugar con la tentación que en vencerla. Pedro fue el hombre que Dios llamó para levantar la Iglesia, darle forma, cuidarla. Pedro formaría la iglesia de aquel tiempo para que existiera hasta el día de hoy. No podía darse el lujo de caer y seguir derrumbado. Ni tú, ni yo tampoco. Debes abrir bien tus ojos y entender cuál ha sido el plan de Dios para tu vida. Que nadie me turbe, que ni mi propia carne me arrastre, ni mis deseos, ni mi mal. ¡Que nada destruya lo que el Padre ha escogido para mí! Pedro era un hombre fogoso e impetuoso, pronto a contestar, pronto a decir y opinar. Eso Satanás lo tomó como ventaja y caminó detrás de él para destruirlo. Por tal razón debemos de entender que nuestra lucha no es contra carne y sangre sino contra principados, demonios (Efesios 6: 11,12), contra tanto mal, para que no alcancemos, para que no lleguemos, para que perezcamos a mitad de camino, para que no lleguemos hasta el fin y nuestros sentimientos se confundan. No le demos oportunidades al enemigo. Satanás viene a robar, y algo muy importante que quiere robar es la fe. Si logra destruir tu fe ya no agradarías a Dios, porque sin fe es imposible agradar a Dios (Hebreos 11:6). Jesús le dijo a Pedro, \"Yo he rogado para que tu fe no falte.\" Porque si tu fe faltara ya no hay nada más que hacer, porque cuando no tenemos fe, no podemos mover la mano de Dios, pues la mano de Dios sólo la mueven los justos que tienen fe. El que se acerca a Dios es necesario que le crea, y para creerle hay que tener fe. Que digas como Pablo, \"He guardado la fe.\" Doy un consejo a los padres: levántense a orar y luchar con armas espirituales por sus hijos, pues Satanás los ha pedido para zarandearlos y ustedes no le pueden seguir el juego a Satanás. Jesús continuó, \"Pedro vas a caer, pero cuando te levantes ve y confirma a los hermanos.\" Que la tentación no nos turbe, de hecho, no hay ninguna razón justa para caer en la tentación, pues Dios quiere que seas firme, que seas estable. Aunque parece que a muchos se les hace fácil dejar el camino del Señor, pero muy difícil les será el día que tengan que dar cuenta. Hermano, Satanás está vencido porque Jesús lo venció por ti, así que si hubieras caído levántate y luego que te levantes mira la mano del Dios grande que se extiende hacia ti. Que perezca el mundo si quiere, pero que tu alma no se pierda sino que seas salvo y victorioso para la eternidad. Amén.",
    "contenido_renderizado": [
      {
        "tipo": "parrafo",
        "texto": "Detrás de cada guerra, sea cuál sea, Satanás está. Tenemos que saberlo y entenderlo, que nuestra lucha es con Satanás, por eso tenemos que vivir conscientes de lo que dice la Escritura. Pues el diablo está detrás de cada divorcio, de cada vicio, de cada mala decisión que tomamos, etc. Él siempre está buscando cómo destruir nuestras vidas, día y noche, para después que te destruya burlarse de ti. (1 Pedro 5: 8) Pero la Iglesia tiene tres poderosas armas para romper con los planes de nuestro enemigo el diablo: el ayuno, la oración y conocer las Escrituras. Si conociéramos las Escrituras sabríamos qué hacer cuando el mal nos asecha. (2 Timoteo 3: 16,17) Pero lamentablemente, casi siempre hacemos otra cosa, buscamos a otro para que nos escuche y nos aconseje. Mientras los apóstoles discutían sobre lo que era superficial, quien sería el mayor entre ellos (Lucas 22:24), Satanás buscaba como podía destruirlos uno a uno. Y posiblemente dijo: \"Atacaré al más vulnerable, al más fácil, ¡Atacaré a Pedro!\" (Lucas 22:31) Satanás pidió eso y se le concedió. Cuando nos convertimos de nuestros malos caminos, Satanás comienza a hacer planes para ver cómo nos hace retroceder y cómo nos puede destruir. Entonces, busca lo más frágil, lo más vulnerable en nosotros. Es por eso que tenemos que estar conscientes de quiénes somos y cómo somos. En medio de los apóstoles ya Satanás había destruido a uno (a Judas), ya lo había tumbado, pues lo conquistó por sus ambiciones, por su avaricia. Satanás había observado bien a Judas, descubrió su mal, sus tendencias al mal, las cuales usaría para destruirlo. Por eso debemos examinarnos y renunciar a lo que nos puede hacer caer. (2 Corintios 13: 5) Ten en cuenta que lo que Satanás sugiere a nuestros oídos, a la mente, tú lo puedes resistir. Cuando cedes es porque te place, pues ninguna tentación es sobrenatural, todas son humanas, pues con la tentación tenemos siempre la salida para que podamos soportar (1ra Cor. 10:13). Día y noche él está acusando a los hijos de Dios delante del trono sobre el carácter, sobre nuestras malas obras, sobre la murmuración, etc. No le demos lugar al diablo. Iglesia, no existe ninguna razón para ceder ante la tentación. ¿Es tan grande la pasión para pecar? ¿Por qué ceder si luego vamos a llorar y a lamentar? Si luego será la vergüenza. ¿Serán más grandes la vil tentación y el deseo hacia lo malo que el amor de Jesús? ¿Entregaré yo mi vida al mal así porque sí? Consideremos que el Padre quitó la desgracia de nuestras vidas. Me ha cuidado, me ha dado vida eterna, quitó la maldición (Gálatas 3: 13, 14) y todos los juicios. Entonces, ¿cómo yo voy a ceder a la tentación si el Padre me ha dado tanto? Pesemos en balanza cuál es más grande, ¿la tentación que el diablo nos tiende para destruirnos o el amor que el Padre ha tenido con nuestras vidas? El Padre prepara todo lo que es puro, todo lo bueno. Él es justo, fiel. Por el otro lado, Satanás prepara con traición, con burla, con todo lo que es sucio, prepara para todo lo que te va a causar vergüenza, dolor, daño para ti y para los que están a tu alrededor. Dentro de nosotros hay una batalla de la carne y el espíritu y es más fácil ceder a todo lo que es carne. Cuando cedemos vamos rumbo a la destrucción, y después al pasar el tiempo decimos, \"Fue que no pude.\" No debe ser. Pues hay algo que se llama \"tiempo\", y el \"tiempo\" trae la vejez y junto con la vejez se van las fuerzas, el ánimo, el deseo de hacer lo bueno, la capacidad de poder actuar bien que se va con los días, y Satanás vino y destruyó lo que era el plan de Dios, el plan perfecto. No te engañes tú mismo. Sucede que decimos que lo que es correcto es lo que nosotros pensamos y creemos. Pero eso es producto de nuestro orgullo. Y a veces nos convertimos en el apoyo de lo que está mal. No apoyes nunca lo malo, porque cuando lo hacemos estamos diciéndole al mal, \"Ven entra a mi casa.\" Aunque te digan que eres muy estricto, que eres muy fuerte, no permitas entrar el mal a tu casa, porque Satanás viene para matar, robar y destruir. (Juan 10: 10) Pedro no entendió lo que Jesús le advertía, \"Pedro, Satanás te ha pedido para zarandearos, pero yo he rogado por ti, que tu fe no falte.\" Y pensar que nosotros tomamos la vida como si fuera tan fácil y la luchamos a flor de piel y pasamos la vida como un juego y los días como si nada, y nos olvidamos de Dios, de los dones que nos da, de los ministerios. Y muchos se ocupan más en jugar con la tentación que en vencerla. Pedro fue el hombre que Dios llamó para levantar la Iglesia, darle forma, cuidarla. Pedro formaría la iglesia de aquel tiempo para que existiera hasta el día de hoy. No podía darse el lujo de caer y seguir derrumbado. Ni tú, ni yo tampoco. Debes abrir bien tus ojos y entender cuál ha sido el plan de Dios para tu vida. Que nadie me turbe, que ni mi propia carne me arrastre, ni mis deseos, ni mi mal. ¡Que nada destruya lo que el Padre ha escogido para mí! Pedro era un hombre fogoso e impetuoso, pronto a contestar, pronto a decir y opinar. Eso Satanás lo tomó como ventaja y caminó detrás de él para destruirlo. Por tal razón debemos de entender que nuestra lucha no es contra carne y sangre sino contra principados, demonios (Efesios 6: 11,12), contra tanto mal, para que no alcancemos, para que no lleguemos, para que perezcamos a mitad de camino, para que no lleguemos hasta el fin y nuestros sentimientos se confundan. No le demos oportunidades al enemigo. Satanás viene a robar, y algo muy importante que quiere robar es la fe. Si logra destruir tu fe ya no agradarías a Dios, porque sin fe es imposible agradar a Dios (Hebreos 11:6). Jesús le dijo a Pedro, \"Yo he rogado para que tu fe no falte.\" Porque si tu fe faltara ya no hay nada más que hacer, porque cuando no tenemos fe, no podemos mover la mano de Dios, pues la mano de Dios sólo la mueven los justos que tienen fe. El que se acerca a Dios es necesario que le crea, y para creerle hay que tener fe. Que digas como Pablo, \"He guardado la fe.\" Doy un consejo a los padres: levántense a orar y luchar con armas espirituales por sus hijos, pues Satanás los ha pedido para zarandearlos y ustedes no le pueden seguir el juego a Satanás. Jesús continuó, \"Pedro vas a caer, pero cuando te levantes ve y confirma a los hermanos.\" Que la tentación no nos turbe, de hecho, no hay ninguna razón justa para caer en la tentación, pues Dios quiere que seas firme, que seas estable. Aunque parece que a muchos se les hace fácil dejar el camino del Señor, pero muy difícil les será el día que tengan que dar cuenta. Hermano, Satanás está vencido porque Jesús lo venció por ti, así que si hubieras caído levántate y luego que te levantes mira la mano del Dios grande que se extiende hacia ti. Que perezca el mundo si quiere, pero que tu alma no se pierda sino que seas salvo y victorioso para la eternidad. Amén.",
        "referencias_inline": [
          "1 Pedro 5:8",
          "2 Timoteo 3:16,17",
          "Lucas 22:24",
          "Lucas 22:31",
          "2 Corintios 13:5",
          "Gálatas 3:13,14",
          "Juan 10:10",
          "Efesios 6:11,12",
          "Hebreos 11:6"
        ]
      }
    ]
  },
  "busqueda": {
    "texto_indexable": "la tentacion de pedro y su levantarse lucas 22 31 satanas oracion tentacion liderazgo espiritual familia vida eterna oracion juicio arrepentimiento escrituras detras de cada guerra sea cual sea satanas esta tenemos que saberlo y entenderlo que nuestra lucha es con satanas por eso tenemos que vivir conscientes de lo que dice la escritura pues el diablo esta detras de cada divorcio de cada vicio de cada mala decision que tomamos etc el siempre esta buscando como destruir nuestras vidas dia y noche para despues que te destruya burlarse de ti 1 pedro 5 8 pero la iglesia tiene tres poderosas armas para romper con los planes de nuestro enemigo el diablo el ayuno la oracion y conocer las escrituras si conocieramos las escrituras sabriamos que hacer cuando el mal nos asecha 2 timoteo 3 16 17 pero lamentablemente casi siempre hacemos otra cosa buscamos a otro para que nos escuche y nos aconseje mientras los apostoles discutian sobre lo que era superficial quien seria el mayor entre ellos lucas 22 24 satanas buscaba como podia destruirlos uno a uno y posiblemente dijo atacare al mas vulnerable al mas facil atacare a pedro lucas 22 31 satanas pidio eso y se le concedio cuando nos convertimos de nuestros malos caminos satanas comienza a hacer planes para ver como nos hace retroceder y como nos puede destruir entonces busca lo mas fragil lo mas vulnerable en nosotros es por eso que tenemos que estar conscientes de quienes somos y como somos en medio de los apostoles ya satanas habia destruido a uno a judas ya lo habia tumbado pues lo conquisto por sus ambiciones por su avaricia satanas habia observado bien a judas descubrio su mal sus tendencias al mal las cuales usaria para destruirlo por eso debemos examinarnos y renunciar a lo que nos puede hacer caer 2 corintios 13 5 ten en cuenta que lo que satanas sugiere a nuestros oidos a la mente tu lo puedes resistir cuando cedes es porque te place pues ninguna tentacion es sobrenatural todas son humanas pues con la tentacion tenemos siempre la salida para que podamos soportar 1ra cor 10 13 dia y noche el esta acusando a los hijos de Dios delante del trono sobre el caracter sobre nuestras malas obras sobre la murmuracion etc no le demos lugar al diablo iglesia no existe ninguna razon para ceder ante la tentacion es tan grande la pasion para pecar por que ceder si luego vamos a llorar y a lamentar si luego sera la verguenza seran mas grandes la vil tentacion y el deseo hacia lo malo que el amor de Jesus entregare yo mi vida al mal asi porque si consideremos que el padre quito la desgracia de nuestras vidas me ha cuidado me ha dado vida eterna quito la maldicion galatas 3 13 14 y todos los juicios entonces como yo voy a ceder a la tentacion si el padre me ha dado tanto pesemos en balanza cual es mas grande la tentacion que el diablo nos tiende para destruirnos o el amor que el padre ha tenido con nuestras vidas el padre prepara todo lo que es puro todo lo bueno el es justo fiel por el otro lado satanas prepara con traicion con burla con todo lo que es sucio prepara para todo lo que te va a causar verguenza dolor dano para ti y para los que estan a tu alrededor dentro de nosotros hay una batalla de la carne y el espiritu y es mas facil ceder a todo lo que es carne cuando cedemos vamos rumbo a la destruccion y despues al pasar el tiempo decimos fue que no pude no debe ser pues hay algo que se llama tiempo y el tiempo trae la vejez y junto con la vejez se van las fuerzas el animo el deseo de hacer lo bueno la capacidad de poder actuar bien que se va con los dias y satanas vino y destruyo lo que era el plan de Dios el plan perfecto no te enganes tu mismo sucede que decimos que lo que es correcto es lo que nosotros pensamos y creemos pero eso es producto de nuestro orgullo y a veces nos convertimos en el apoyo de lo que esta mal no apoyes nunca lo malo porque cuando lo hacemos estamos diciendole al mal ven entra a mi casa aunque te digan que eres muy estricto que eres muy fuerte no permitas entrar el mal a tu casa porque satanas viene para matar robar y destruir juan 10 10 pedro no entendio lo que Jesus le advertia pedro satanas te ha pedido para zarandearos pero yo he rogado por ti que tu fe no falte y pensar que nosotros tomamos la vida como si fuera tan facil y la luchamos a flor de piel y pasamos la vida como un juego y los dias como si nada y nos olvidamos de Dios de los dones que nos da de los ministerios y muchos se ocupan mas en jugar con la tentacion que en vencerla pedro fue el hombre que Dios llamo para levantar la iglesia darle forma cuidarla pedro formaria la iglesia de aquel tiempo para que existiera hasta el dia de hoy no podia darse el lujo de caer y seguir derrumbado ni tu ni yo tampoco debes abrir bien tus ojos y entender cual ha sido el plan de Dios para tu vida que nadie me turbe que ni mi propia carne me arrastre ni mis deseos ni mi mal que nada destruya lo que el padre ha escogido para mi pedro era un hombre fogoso e impetuoso pronto a contestar pronto a decir y opinar eso satanas lo tomo como ventaja y camino detras de el para destruirlo por tal razon debemos de entender que nuestra lucha no es contra carne y sangre sino contra principados demonios efesios 6 11 12 contra tanto mal para que no alcancemos para que no lleguemos para que perezcamos a mitad de camino para que no lleguemos hasta el fin y nuestros sentimientos se confundan no le demos oportunidades al enemigo satanas viene a robar y algo muy importante que quiere robar es la fe si logra destruir tu fe ya no agradarias a Dios porque sin fe es imposible agradar a Dios hebreos 11 6 Jesus le dijo a pedro yo he rogado para que tu fe no falte porque si tu fe faltara ya no hay nada mas que hacer porque cuando no tenemos fe no podemos mover la mano de Dios pues la mano de Dios solo la mueven los justos que tienen fe el que se acerca a Dios es necesario que le crea y para creerle hay que tener fe que digas como pablo he guardado la fe doy un consejo a los padres levantense a orar y luchar con armas espirituales por sus hijos pues satanas los ha pedido para zarandearlos y ustedes no le pueden seguir el juego a satanas Jesus continuo pedro vas a caer pero cuando te levantes ve y confirma a los hermanos que la tentacion no nos turbe de hecho no hay ninguna razon justa para caer en la tentacion pues Dios quiere que seas firme que seas estable aunque parece que a muchos se les hace facil dejar el camino del senor pero muy dificil les sera el dia que tengan que dar cuenta hermano satanas esta vencido porque Jesus lo vencio por ti asi que si hubieras caido levantate y luego que te levantes mira la mano del Dios grande que se extiende hacia ti que perezca el mundo si quiere pero que tu alma no se pierda sino que seas salvo y victorioso para la eternidad amen",
    "alias_busqueda": [
      "Estudio 306",
      "Lucas",
      "Lucas 22",
      "Lucas 22:31",
      "vida eterna",
      "oración",
      "juicio",
      "arrepentimiento",
      "Satanás"
    ]
  },
  "revision_manual": {
    "requiere_revision": false,
    "motivo": ""
  },
  "ui": {
    "mostrar_credito_en_header": true,
    "mostrar_numero_estudio": true,
    "mostrar_fecha": true,
    "mostrar_topicos": true,
    "permitir_favorito": true,
    "permitir_compartir": true
  }
}
